<annotation>
	<folder>blech</folder>
	<filename>43.5892984_1.3733514.png</filename>
	<path>/home/muddy/Documents/AdvAna/blech/43.5892984_1.3733514.png</path>
	<source>
		<database>Unknown</database>
	</source>
	<size>
		<width>512</width>
		<height>512</height>
		<depth>3</depth>
	</size>
	<segmented>0</segmented>
	<object>
		<name>pool</name>
		<pose>Unspecified</pose>
		<truncated>0</truncated>
		<difficult>0</difficult>
		<bndbox>
			<xmin>235</xmin>
			<ymin>221</ymin>
			<xmax>278</xmax>
			<ymax>295</ymax>
		</bndbox>
	</object>
</annotation>
